airflow_api_plugin/__init__.py
airflow_api_plugin/config.py
airflow_api_plugin/main.py
airflow_api_plugin/utils.py
airflow_api_plugin/api/__init__.py
airflow_api_plugin/api/api_setup.py
airflow_api_plugin/api/app.py
airflow_api_plugin/api/response.py
airflow_api_plugin/api/endpoints/__init__.py
airflow_api_plugin/api/endpoints/get_serialized_dags.py
airflow_api_plugin/api/schemas/__init__.py
airflow_api_plugin/api/schemas/serialized_dag_schema.py
airflow_api_plugin-1.0.0.dist-info/LICENSE
airflow_api_plugin-1.0.0.dist-info/METADATA
airflow_api_plugin-1.0.0.dist-info/WHEEL
airflow_api_plugin-1.0.0.dist-info/entry_points.txt
airflow_api_plugin-1.0.0.dist-info/top_level.txt
airflow_api_plugin-1.0.0.dist-info/RECORD
