Metadata-Version: 2.1
Name: airflow-api-plugin
Version: 1.0.0
Summary: Exposes 'Aggua' Apache Airflow management capabilities via secure API
Home-page: https://github.com/Aggua/airlfow-aggua-plugin
Author: aggua
Author-email: 
License: GNU AGPLv3
Keywords: apache airflow,aggua,plugin,flask
Platform: UNKNOWN
Classifier: Development Status :: 5 - Production/Stable
Classifier: Intended Audience :: Developers
Classifier: Topic :: Software Development :: Libraries
Classifier: Operating System :: OS Independent
Classifier: License :: OSI Approved :: GNU Affero General Public License v3 or later (AGPLv3+)
Classifier: Programming Language :: Python :: 3
Classifier: Programming Language :: Python :: 3.6
Classifier: Programming Language :: Python :: 3.8
Requires-Python: >=3.6
License-File: LICENSE
Requires-Dist: apache-airflow (>=2.1.0)
Requires-Dist: marshmallow (>=3.14.1)
